fudgeo/__init__.py
fudgeo/alias.py
fudgeo/constant.py
fudgeo/context.py
fudgeo/enumeration.py
fudgeo/geopkg.py
fudgeo/geopkg.sql
fudgeo/sql.py
fudgeo/util.py
fudgeo/extension/__init__.py
fudgeo/extension/metadata.py
fudgeo/extension/ogr.py
fudgeo/extension/schema.py
fudgeo/extension/spatial.py
fudgeo/geometry/__init__.py
fudgeo/geometry/base.py
fudgeo/geometry/linestring.py
fudgeo/geometry/linestring.pyi
fudgeo/geometry/point.py
fudgeo/geometry/point.pyi
fudgeo/geometry/polygon.py
fudgeo/geometry/polygon.pyi
fudgeo/geometry/util.py
fudgeo-1.5.1.dist-info/licenses/LICENSE
fudgeo-1.5.1.dist-info/METADATA
fudgeo-1.5.1.dist-info/WHEEL
fudgeo-1.5.1.dist-info/top_level.txt
fudgeo-1.5.1.dist-info/RECORD
