Metadata-Version: 2.4
Name: fudgeo
Version: 1.5.1
Summary: GeoPackage support from Python.  fudgeo is a lightweight package for creating OGC GeoPackages, Feature Classes, and Tables.  Easily read and write geometries and attributes to Feature Classes and Tables using regular Python objects and SQLite syntax.
Author-email: "Integrated Informatics (USA) Inc." <contact@integrated-informatics.com>
License-Expression: MIT
Project-URL: Homepage, https://github.com/realiii/fudgeo
Keywords: geopackage
Classifier: Programming Language :: Python
Classifier: Programming Language :: Python :: 3
Classifier: Programming Language :: Python :: 3.10
Classifier: Programming Language :: Python :: 3.11
Classifier: Programming Language :: Python :: 3.12
Classifier: Programming Language :: Python :: 3.13
Classifier: Programming Language :: Python :: 3.14
Classifier: Operating System :: OS Independent
Requires-Python: >=3.10
License-File: LICENSE
Requires-Dist: bottleneck>=1.6.0
Requires-Dist: numpy>=2.2.6
Dynamic: license-file
